{
    "data": [
        {
            "underlying": "FINNIFTY",
            "identifier": "FUTIDXFINNIFTY26-08-2021XX0.00",
            "instrumentType": "FUTIDX",
            "instrument": "Index Futures",
            "contract": "FINNIFTY 26-Aug-2021",
            "expiryDate": "26-Aug-2021",
            "optionType": "-",
            "strikePrice": 0,
            "lastPrice": 17294.3,
            "change": -144.45,
            "pChange": -0.83,
            "volume": 2080,
            "totalTurnover": 36039660.8,
            "value": 36039660.8,
            "premiumTurnOver": 36039660.8,
            "underlyingValue": 17282.65,
            "openInterest": 95,
            "noOfTrades": 52,
            "meta": {
                "data": [],
                "msg": "No Data Found"
            }
        },
        {
            "underlying": "FINNIFTY",
            "identifier": "FUTIDXFINNIFTY18-08-2021XX0.00",
            "instrumentType": "FUTIDX",
            "instrument": "Index Futures",
            "contract": "FINNIFTY 18-Aug-2021",
            "expiryDate": "18-Aug-2021",
            "optionType": "-",
            "strikePrice": 0,
            "lastPrice": 17379.95,
            "change": 19.8,
            "pChange": 0.11,
            "volume": 480,
            "totalTurnover": 8332320,
            "value": 8332320,
            "premiumTurnOver": 8332320,
            "underlyingValue": 17282.65,
            "openInterest": 6,
            "noOfTrades": 12,
            "meta": {
                "data": [],
                "msg": "No Data Found"
            }
        },
        {
            "underlying": "FINNIFTY",
            "identifier": "FUTIDXFINNIFTY30-09-2021XX0.00",
            "instrumentType": "FUTIDX",
            "instrument": "Index Futures",
            "contract": "FINNIFTY 30-Sep-2021",
            "expiryDate": "30-Sep-2021",
            "optionType": "-",
            "strikePrice": 0,
            "lastPrice": 17369,
            "change": -107.45,
            "pChange": -0.61,
            "volume": 160,
            "totalTurnover": 2780721.5999999996,
            "value": 2780721.5999999996,
            "premiumTurnOver": 2780721.5999999996,
            "underlyingValue": 17282.65,
            "openInterest": 19,
            "noOfTrades": 4,
            "meta": {
                "data": [],
                "msg": "No Data Found"
            }
        }
    ],
    "timestamp": "17-Aug-2021 13:22:53",
    "marketStatus": {
        "market": "FO",
        "marketOpenOrClose": "Open",
        "marketCurrentTradingDate": "Aug 17,2021",
        "marketOpenTime": "0915",
        "marketCloseTime": "1530",
        "marketPreviousTradingDate": "Aug 16,2021",
        "marketNextTradingDate": "Aug 18,2021",
        "marketStatusMessage": "Market is Open"
    }
}